cmem_plugin_pyshacl/__init__.py
cmem_plugin_pyshacl/plugin_pyshacl.py
cmem_plugin_pyshacl/pyshacl.svg
cmem_plugin_pyshacl-5.3.0.dist-info/METADATA
cmem_plugin_pyshacl-5.3.0.dist-info/WHEEL
cmem_plugin_pyshacl-5.3.0.dist-info/licenses/LICENSE
cmem_plugin_pyshacl-5.3.0.dist-info/RECORD
