Metadata-Version: 2.4
Name: cmem-plugin-pyshacl
Version: 5.3.0
Summary: Validate your Knowledge Graphs based on tests generated from SHACL shapes.
License: Apache-2.0
License-File: LICENSE
Keywords: eccenca Corporate Memory,plugin,SHACL
Author: eccenca GmbH
Author-email: cmempy-developer@eccenca.com
Requires-Python: >=3.11,<4.0
Classifier: Development Status :: 4 - Beta
Classifier: Environment :: Plugins
Classifier: License :: OSI Approved :: Apache Software License
Classifier: Programming Language :: Python :: 3
Classifier: Programming Language :: Python :: 3.11
Classifier: Programming Language :: Python :: 3.12
Classifier: Programming Language :: Python :: 3.13
Classifier: Programming Language :: Python :: 3.14
Requires-Dist: cmem-cmempy (>=25.2.0,<26.0.0)
Requires-Dist: cmem-plugin-base (>=4.12.1,<5.0.0)
Requires-Dist: pyshacl (>=0.30.1,<0.31.0)
Requires-Dist: rdflib (>=7.1.4,<8.0.0)
Requires-Dist: validators (>=0.35.0,<0.36.0)
Project-URL: Homepage, https://github.com/eccenca/cmem-plugin-pyshacl
